{
  "_appTitle": "Chatopera 文档中心 - 聊天机器人、智能客服、人工智能、智能问答、业务流程自动化、对话机器人、聊天机器人平台",
  "_appFooter": "©2020 <a href=\"https://www.chatopera.com\" target=\"_blank\">北京华夏春松科技有限公司</a> 京ICP备17070907号-1",
  "_appLogoPath": "images/logo.png",
  "_appFaviconPath": "images/favicon.ico",
  "_description": "聊天机器人、智能客服、人工智能、智能问答、业务流程自动化、对话机器人、聊天机器人平台。 Chatopera 帮助企业使用聊天机器人提升自动化。",
  "_enableSearch": true,
  "_enableNewTab": true,
  "_disableNavbar": false,
  "_disableBreadcrumb": false,
  "_disableToc": false,
  "_disableAffix": false,
  "_disableContribution": true,
  "_gitContribute": false,
  "_noindex": false
}
